{"route_id":"60324","trips":[{"trip_id":"60324_A_N_0530","service":"N","times":[330,332,337]},{"trip_id":"60324_A_N_0830","service":"N","times":[510,512,517]},{"trip_id":"60324_A_N_1130","service":"N","times":[690,692,697]},{"trip_id":"60324_A_N_1430","service":"N","times":[870,872,877]},{"trip_id":"60324_A_N_1730","service":"N","times":[1050,1052,1057]},{"trip_id":"60324_A_N_2030","service":"N","times":[1230,1232,1237]},{"trip_id":"60324_A_RD_0400","service":"RD","times":[240,242,247]},{"trip_id":"60324_A_RD_0530","service":"RD","times":[330,332,337]},{"trip_id":"60324_A_RD_0700","service":"RD","times":[420,422,427]},{"trip_id":"60324_A_RD_0830","service":"RD","times":[510,512,517]},{"trip_id":"60324_A_RD_1000","service":"RD","times":[600,602,607]},{"trip_id":"60324_A_RD_1130","service":"RD","times":[690,692,697]},{"trip_id":"60324_A_RD_1300","service":"RD","times":[780,782,787]},{"trip_id":"60324_A_RD_1430","service":"RD","times":[870,872,877]},{"trip_id":"60324_A_RD_1600","service":"RD","times":[960,962,967]},{"trip_id":"60324_A_RD_1730","service":"RD","times":[1050,1052,1057]},{"trip_id":"60324_A_RD_1900","service":"RD","times":[1140,1142,1147]},{"trip_id":"60324_A_RD_2030","service":"RD","times":[1230,1232,1237]},{"trip_id":"60324_A_S_0530","service":"S","times":[330,332,337]},{"trip_id":"60324_A_S_0830","service":"S","times":[510,512,517]},{"trip_id":"60324_A_S_1130","service":"S","times":[690,692,697]},{"trip_id":"60324_A_S_1430","service":"S","times":[870,872,877]},{"trip_id":"60324_A_S_1730","service":"S","times":[1050,1052,1057]},{"trip_id":"60324_A_S_2030","service":"S","times":[1230,1232,1237]}]}