{"route_id":"60333-1","trips":[{"trip_id":"60333_B_N_0445","service":"N","times":[330]},{"trip_id":"60333_B_N_0630","service":"N","times":[435]},{"trip_id":"60333_B_N_0730","service":"N","times":[495]},{"trip_id":"60333_B_N_0830","service":"N","times":[555]},{"trip_id":"60333_B_N_0930","service":"N","times":[615]},{"trip_id":"60333_B_N_1030","service":"N","times":[675]},{"trip_id":"60333_B_N_1230","service":"N","times":[795]},{"trip_id":"60333_B_N_1530","service":"N","times":[975]},{"trip_id":"60333_B_N_1730","service":"N","times":[1095]},{"trip_id":"60333_B_N_1930","service":"N","times":[1215]},{"trip_id":"60333_B_N_2130","service":"N","times":[1335]},{"trip_id":"60333_B_N_2330","service":"N","times":[1455]},{"trip_id":"60333_B_RD_0445","service":"RD","times":[330]},{"trip_id":"60333_B_RD_0630","service":"RD","times":[435]},{"trip_id":"60333_B_RD_0730","service":"RD","times":[495]},{"trip_id":"60333_B_RD_0830","service":"RD","times":[555]},{"trip_id":"60333_B_RD_0930","service":"RD","times":[615]},{"trip_id":"60333_B_RD_1030","service":"RD","times":[675]},{"trip_id":"60333_B_RD_1230","service":"RD","times":[795]},{"trip_id":"60333_B_RD_1530","service":"RD","times":[975]},{"trip_id":"60333_B_RD_1730","service":"RD","times":[1095]},{"trip_id":"60333_B_RD_1930","service":"RD","times":[1215]},{"trip_id":"60333_B_RD_2130","service":"RD","times":[1335]},{"trip_id":"60333_B_RD_2330","service":"RD","times":[1455]},{"trip_id":"60333_B_S_0445","service":"S","times":[330]},{"trip_id":"60333_B_S_0630","service":"S","times":[435]},{"trip_id":"60333_B_S_0730","service":"S","times":[495]},{"trip_id":"60333_B_S_0830","service":"S","times":[555]},{"trip_id":"60333_B_S_0930","service":"S","times":[615]},{"trip_id":"60333_B_S_1030","service":"S","times":[675]},{"trip_id":"60333_B_S_1230","service":"S","times":[795]},{"trip_id":"60333_B_S_1530","service":"S","times":[975]},{"trip_id":"60333_B_S_1730","service":"S","times":[1095]},{"trip_id":"60333_B_S_1930","service":"S","times":[1215]},{"trip_id":"60333_B_S_2130","service":"S","times":[1335]},{"trip_id":"60333_B_S_2330","service":"S","times":[1455]}]}